taxonomy/__init__.py
taxonomy/api_client.py
taxonomy/configuration.py
taxonomy/rest.py
taxonomy/api/__init__.py
taxonomy/api/admins_api.py
taxonomy/api/developers_api.py
taxonomy/api/public_api.py
taxonomy/models/__init__.py
taxonomy/models/additional_type.py
taxonomy/models/error_model.py
taxonomy/models/hybrid_type.py
taxonomy/models/taxon_entry_list_type.py
taxonomy/models/taxon_entry_type.py
taxonomy/models/taxon_type.py
test/__init__.py
test/test_additional_type.py
test/test_admins_api.py
test/test_developers_api.py
test/test_error_model.py
test/test_hybrid_type.py
test/test_public_api.py
test/test_taxon_entry_list_type.py
test/test_taxon_entry_type.py
test/test_taxon_type.py
sysnet_taxonomy-1.0.1.1.dist-info/METADATA
sysnet_taxonomy-1.0.1.1.dist-info/WHEEL
sysnet_taxonomy-1.0.1.1.dist-info/top_level.txt
sysnet_taxonomy-1.0.1.1.dist-info/RECORD
