Metadata-Version: 2.1
Name: sysnet-taxonomy
Version: 1.0.1.1
Summary: SYSNET CITES Taxonomy REST API client
Home-page: 
Author-email: Radim Jaeger <rjaeger@sysnet.cz>
Project-URL: Homepage, https://github.com/SYSNET-CZ/swagger/tree/main/clients/taxonomy
Classifier: Programming Language :: Python :: 3
Classifier: License :: OSI Approved :: Apache Software License
Classifier: Operating System :: OS Independent
Classifier: Topic :: Internet :: WWW/HTTP :: Dynamic Content
Requires-Python: >=3.9
